circuitsim_janq0/__init__.py
circuitsim_janq0-0.0.5.dist-info/METADATA
circuitsim_janq0-0.0.5.dist-info/WHEEL
circuitsim_janq0-0.0.5.dist-info/entry_points.txt
circuitsim_janq0-0.0.5.dist-info/licenses/LICENSE.md
circuitsim_janq0-0.0.5.dist-info/RECORD
